inspect_mate_pp/__init__.py
inspect_mate_pp-0.0.4.dist-info/LICENSE.txt
inspect_mate_pp-0.0.4.dist-info/METADATA
inspect_mate_pp-0.0.4.dist-info/WHEEL
inspect_mate_pp-0.0.4.dist-info/RECORD
