Metadata-Version: 2.1
Name: inspect-mate-pp
Version: 0.0.4
Summary: 
Author: Jacob Valdez
Author-email: jacobfv123@gmail.com
Requires-Python: >=3.5.0
Classifier: Programming Language :: Python :: 3
Classifier: Programming Language :: Python :: 3.5
Classifier: Programming Language :: Python :: 3.6
Classifier: Programming Language :: Python :: 3.7
Classifier: Programming Language :: Python :: 3.8
Classifier: Programming Language :: Python :: 3.9
Classifier: Programming Language :: Python :: 3.10
Classifier: Programming Language :: Python :: 3.11
